plot_phylo/__init__.py
plot_phylo/_version.py
plot_phylo/plot_phylo.py
plot_phylo-0.1.11.data/scripts/plot_phylo.py
plot_phylo-0.1.11.dist-info/LICENSE
plot_phylo-0.1.11.dist-info/METADATA
plot_phylo-0.1.11.dist-info/WHEEL
plot_phylo-0.1.11.dist-info/top_level.txt
plot_phylo-0.1.11.dist-info/RECORD
