Metadata-Version: 2.1
Name: plot-phylo
Version: 0.1.11
Summary: This module allows the user to plot a phylogenetic tree on an existing matplotlib axis.
Home-page: https://github.com/KatyBrown/plot_phylo
Author: Katy Brown, Duncan Cross
Author-email: Katy Brown <kab84@cam.ac.uk>
Maintainer-email: Katy Brown <kab84@cam.ac.uk>
License: MIT License
Project-URL: Documentation, https://plot-phylo.readthedocs.io
Project-URL: Repository, https://github.com/KatyBrown/plot_phylo
Project-URL: Bug Tracker, https://github.com/KatyBrown/plot_phylo/issues
Keywords: phylogenetics,matplotlib
Requires-Python: >=3.6
License-File: LICENSE
Requires-Dist: ete3>=3.1.0
Requires-Dist: matplotlib>=2.1.1
